bit_counter.sv
module bit_counter(

    input  logic clk,
    input  logic rst,
    input  logic clear,
    input  logic count_en,

    output logic [3:0] count,
    output logic last
);

always_ff @(posedge clk or posedge rst) begin

    if(rst)
        count <= 4'd0;

    else if(clear)
        count <= 4'd0;

    else if(count_en)
        count <= count + 1'b1;

end

assign last = (count == 4'd7);

endmodule

tb_bit_counter.sv
`timescale 1ns/1ps

module tb_bit_counter;
    // Testbench Signals
    bit clk, rst;
    bit clear, count_en;

    bit [3:0] count;
    bit last;

    bit [3:0] expected_count;
    bit expected_last;

    
    // Instantiate DUT
    bit_counter dut (
        .clk(clk),
        .rst(rst),
        .clear(clear),
        .count_en(count_en),
        .count(count),
        .last(last)
    );

    
    // Clock generation - 10ns period

    initial begin
        clk = 0;
        forever #5 clk = ~clk;
    end

    //========================================================
    // Checker Scoreboard
    //========================================================

    task checker_scoreboard;

        input [3:0] expected_count;
        input expected_last;
        input string test_name;

        if(count == expected_count && last == expected_last)

            $display("%s Test Passed: count=%0d, last=%0b",
                     test_name, count, last);

        else

            $error("%s Test Failed: DUT - count=%0d, last=%0b | Expected - count=%0d, last=%0b",
                    test_name,
                    count,
                    last,
                    expected_count,
                    expected_last);

    endtask

    //========================================================
    // Apply Inputs Task
    //========================================================

    task apply_inputs;

        input bit rst_, clear_, count_en_;

        rst      = rst_;
        clear    = clear_;
        count_en = count_en_;

        @(posedge clk); // Wait for positive edge
        #1;             // Propagation delay

        $display("Inputs Applied -> rst=%b, clear=%b, count_en=%b",
                  rst, clear, count_en);

    endtask

    //========================================================
    // Main Test Sequence
    //========================================================

    initial begin

    //--------------------------------------------------------
    // TC1 : Reset Test
    //--------------------------------------------------------

        apply_inputs(1, 0, 0);

        expected_count = 0;
        expected_last  = 0;

        checker_scoreboard(expected_count,
                           expected_last,
                           "TC1-Reset");


    //--------------------------------------------------------
    // TC2 : Hold Test
    //--------------------------------------------------------

        apply_inputs(0, 0, 0);

        expected_count = 0;
        expected_last  = 0;

        checker_scoreboard(expected_count,
                           expected_last,
                           "TC2-Hold");


    //--------------------------------------------------------
    // TC3 : Count Enable Test
    //--------------------------------------------------------

        apply_inputs(0, 0, 1);

        expected_count = 1;
        expected_last  = 0;

        checker_scoreboard(expected_count,
                           expected_last,
                           "TC3-Count-1");


    //--------------------------------------------------------
    // TC4 : Consecutive Counting Test
    //--------------------------------------------------------

        repeat(3)
        begin

            apply_inputs(0, 0, 1);

            expected_count = expected_count + 1;
            expected_last  = 0;

            checker_scoreboard(expected_count,
                               expected_last,
                               "TC4-Consecutive-Count");

        end


    //--------------------------------------------------------
    // TC5 : Clear Test
    //--------------------------------------------------------

        apply_inputs(0, 1, 1);

        expected_count = 0;
        expected_last  = 0;

        checker_scoreboard(expected_count,
                           expected_last,
                           "TC5-Clear");


    //--------------------------------------------------------
    // TC6 : Last Signal Assert Test
    //--------------------------------------------------------

        repeat(7)
        begin

            apply_inputs(0, 0, 1);

            expected_count = expected_count + 1;

            if(expected_count == 7)
                expected_last = 1;
            else
                expected_last = 0;

        end

        checker_scoreboard(expected_count,
                           expected_last,
                           "TC6-Last-Assert");


    //--------------------------------------------------------
    // TC7 : Last Signal Deassert Test
    //--------------------------------------------------------

        apply_inputs(0, 0, 1);

        expected_count = expected_count + 1;
        expected_last  = 0;

        checker_scoreboard(expected_count,
                           expected_last,
                           "TC7-Last-Deassert");


    //--------------------------------------------------------
    // TC8 : Reset Priority Test
    // rst + count_en together
    //--------------------------------------------------------

        apply_inputs(1, 0, 1);

        expected_count = 0;
        expected_last  = 0;

        checker_scoreboard(expected_count,
                           expected_last,
                           "TC8-Reset-Priority");


    //--------------------------------------------------------
    // TC9 : Clear Priority Test
    // clear + count_en together
    //--------------------------------------------------------

        apply_inputs(0, 1, 1);

        expected_count = 0;
        expected_last  = 0;

        checker_scoreboard(expected_count,
                           expected_last,
                           "TC9-Clear-Priority");


    //--------------------------------------------------------
    // TC10 : Overflow Test
    //--------------------------------------------------------

        repeat(20)
        begin

            apply_inputs(0, 0, 1);

            expected_count = expected_count + 1;
            expected_last  = (expected_count == 7);

        end

        checker_scoreboard(expected_count,
                           expected_last,
                           "TC10-Overflow");


    //--------------------------------------------------------
    // Randomized Testing
    //--------------------------------------------------------

        repeat(10)
        begin

            clear    = $random;
            count_en = $random;

            apply_inputs(0, clear, count_en);

            if(clear)
                expected_count = 0;

            else if(count_en)
                expected_count = expected_count + 1;

            expected_last = (expected_count == 7);

            checker_scoreboard(expected_count,
                               expected_last,
                               "Random-Test");

        end

        $display("=================================");
        $display("All Testcases Completed");
        $display("=================================");

        $finish;

    end

    initial begin
        $dumpfile("tb_bit_counter.vcd");
        $dumpvars(0, tb_bit_counter);
    end

    initial begin
        #100000;

        $error("ERROR : Simulation timeout!");

        $finish;
    end

endmodule

tb_bit_counter.vcd
$date
	Mon Jun 29 16:33:03 2026
$end
$version
	Icarus Verilog
$end
$timescale
	1ps
$end
$scope module tb_bit_counter $end
$var wire 1 ! last $end
$var wire 4 " count [3:0] $end
$var reg 1 # clear $end
$var reg 1 $ clk $end
$var reg 1 % count_en $end
$var reg 4 & expected_count [3:0] $end
$var reg 1 ' expected_last $end
$var reg 1 ( rst $end
$scope module dut $end
$var wire 1 # clear $end
$var wire 1 $ clk $end
$var wire 1 % count_en $end
$var wire 1 ( rst $end
$var wire 1 ) last $end
$var reg 4 * count [3:0] $end
$upscope $end
$scope task apply_inputs $end
$var reg 1 + clear_ $end
$var reg 1 , count_en_ $end
$var reg 1 - rst_ $end
$upscope $end
$scope task checker_scoreboard $end
$var reg 4 . expected_count [3:0] $end
$var reg 1 / expected_last $end
$upscope $end
$upscope $end
$enddefinitions $end
$comment Show the parameter values. $end
$dumpall
$end
#0
$dumpvars
x/
bx .
1-
0,
0+
b0 *
0)
1(
0'
b0 &
0%
0$
0#
b0 "
0!
$end
#5000
1$
#6000
0(
0-
0/
b0 .
#10000
0$
#15000
1$
#16000
1%
1,
#20000
0$
#25000
b1 "
b1 *
1$
#26000
b1 .
b1 &
#30000
0$
#35000
b10 "
b10 *
1$
#36000
b10 .
b10 &
#40000
0$
#45000
b11 "
b11 *
1$
#46000
b11 .
b11 &
#50000
0$
#55000
b100 "
b100 *
1$
#56000
1#
1+
b100 .
b100 &
#60000
0$
#65000
b0 "
b0 *
1$
#66000
0#
0+
b0 .
b0 &
#70000
0$
#75000
b1 "
b1 *
1$
#76000
b1 &
#80000
0$
#85000
b10 "
b10 *
1$
#86000
b10 &
#90000
0$
#95000
b11 "
b11 *
1$
#96000
b11 &
#100000
0$
#105000
b100 "
b100 *
1$
#106000
b100 &
#110000
0$
#115000
b101 "
b101 *
1$
#116000
b101 &
#120000
0$
#125000
b110 "
b110 *
1$
#126000
b110 &
#130000
0$
#135000
1!
1)
b111 "
b111 *
1$
#136000
1/
b111 .
1'
b111 &
#140000
0$
#145000
0!
0)
b1000 "
b1000 *
1$
#146000
b0 "
b0 *
1(
1-
0/
b1000 .
0'
b1000 &
#150000
0$
#155000
1$
#156000
1#
0(
1+
0-
b0 .
b0 &
#160000
0$
#165000
1$
#166000
0#
0+
#170000
0$
#175000
b1 "
b1 *
1$
#176000
b1 &
#180000
0$
#185000
b10 "
b10 *
1$
#186000
b10 &
#190000
0$
#195000
b11 "
b11 *
1$
#196000
b11 &
#200000
0$
#205000
b100 "
b100 *
1$
#206000
b100 &
#210000
0$
#215000
b101 "
b101 *
1$
#216000
b101 &
#220000
0$
#225000
b110 "
b110 *
1$
#226000
b110 &
#230000
0$
#235000
1!
1)
b111 "
b111 *
1$
#236000
1'
b111 &
#240000
0$
#245000
0!
0)
b1000 "
b1000 *
1$
#246000
0'
b1000 &
#250000
0$
#255000
b1001 "
b1001 *
1$
#256000
b1001 &
#260000
0$
#265000
b1010 "
b1010 *
1$
#266000
b1010 &
#270000
0$
#275000
b1011 "
b1011 *
1$
#276000
b1011 &
#280000
0$
#285000
b1100 "
b1100 *
1$
#286000
b1100 &
#290000
0$
#295000
b1101 "
b1101 *
1$
#296000
b1101 &
#300000
0$
#305000
b1110 "
b1110 *
1$
#306000
b1110 &
#310000
0$
#315000
b1111 "
b1111 *
1$
#316000
b1111 &
#320000
0$
#325000
b0 "
b0 *
1$
#326000
b0 &
#330000
0$
#335000
b1 "
b1 *
1$
#336000
b1 &
#340000
0$
#345000
b10 "
b10 *
1$
#346000
b10 &
#350000
0$
#355000
b11 "
b11 *
1$
#356000
b11 &
#360000
0$
#365000
b100 "
b100 *
1$
#366000
b100 .
b100 &
#370000
0$
#375000
b101 "
b101 *
1$
#376000
1+
1#
b101 .
b101 &
#380000
0$
#385000
b0 "
b0 *
1$
#386000
b0 .
b0 &
#390000
0$
#395000
1$
#396000
0,
0%
#400000
0$
#405000
1$
#406000
1,
1%
#410000
0$
#415000
1$
#416000
0+
0#
#420000
0$
#425000
b1 "
b1 *
1$
#426000
0,
1+
0%
1#
b1 .
b1 &
#430000
0$
#435000
b0 "
b0 *
1$
#436000
b0 .
b0 &
#440000
0$
#445000
1$
#450000
0$
#455000
1$
#456000
1,
1%
