multi_reg.sv
module mult_regs(
    input  logic        clk,
    input  logic        rst,
    input  logic        load,
    input  logic        add_en,
    input  logic        shift,
    input  logic [8:0]  sum,
    input  logic [7:0]  a_in,
    input  logic [7:0]  b_in,

    output logic [8:0]  A,
    output logic [7:0]  M,
    output logic [7:0]  Q
);

always_ff @(posedge clk or posedge rst) begin

    if (rst) begin
        A <= 9'd0;
        M <= 8'd0;
        Q <= 8'd0;
    end

    else if (load) begin
        A <= 9'd0;
        M <= a_in;
        Q <= b_in;
    end

    else if (add_en) begin
        A <= sum;
    end

    else if (shift) begin
        {A,Q} <= {A,Q} >> 1;
    end

end

endmodule

tb_multi_reg.sv
`timescale 1ns/1ps

module tb_mult_regs;

    bit clk;
    bit rst;
    bit load;
    bit add_en;
    bit shift;
    bit [7:0] a_in;
    bit [7:0] b_in;
    bit [8:0] sum;
    
    wire [8:0] A;
    wire [7:0] M;
    wire [7:0] Q;

    bit [8:0] expected_A;
    bit [7:0] expected_M;
    bit [7:0] expected_Q;

    mult_regs dut (
        .clk(clk),
        .rst(rst),
        .load(load),
        .add_en(add_en),
        .shift(shift),
        .a_in(a_in),
        .b_in(b_in),
        .sum(sum),
        .A(A),
        .M(M),
        .Q(Q)
    );

    initial begin
        clk = 0;
        forever #5 clk = ~clk;
    end

    task checker_scoreboard(input string test_name);
        begin
            if ((A === expected_A) && (M === expected_M) && (Q === expected_Q)) begin
                $display("%s Passed: A=%h, M=%h, Q=%h", test_name, A, M, Q);
            end else begin
                $error("%s Failed: Got A=%h, M=%h, Q=%h | Exp: A=%h, M=%h, Q=%h", 
                       test_name, A, M, Q, expected_A, expected_M, expected_Q);
            end
        end
    endtask

    initial begin
        load = 0; add_en = 0; shift = 0; a_in = 0; b_in = 0; sum = 0;
        rst = 1;
        repeat (2) @(posedge clk);
        #1;
        rst = 0;
        expected_A = 0; expected_M = 0; expected_Q = 0;
        checker_scoreboard("Reset_Check");

        load = 1; a_in = 8'd45; b_in = 8'd12;
        @(posedge clk);
        #1;
        load = 0;
        expected_A = 0; expected_M = 8'd45; expected_Q = 8'd12;
        checker_scoreboard("Load_Check");

        sum = 9'd135; add_en = 1;
        @(posedge clk);
        #1;
        add_en = 0;
        expected_A = 9'd135; expected_M = 8'd45; expected_Q = 8'd12;
        checker_scoreboard("Add_Check");

        shift = 1;
        expected_A = expected_A; 
        expected_Q = expected_Q;
        {expected_A, expected_Q} = {expected_A, expected_Q} >> 1;
        @(posedge clk);
        #1;
        shift = 0;
        checker_scoreboard("Shift_Check_1");

        shift = 1;
        {expected_A, expected_Q} = {expected_A, expected_Q} >> 1;
        @(posedge clk);
        #1;
        shift = 0;
        checker_scoreboard("Shift_Check_2");

        load = 1; add_en = 1; shift = 1;
        a_in = 8'd10; b_in = 8'd20; sum = 9'd50;
        @(posedge clk);
        #1;
        load = 0; add_en = 0; shift = 0;
        expected_A = 0; expected_M = 8'd10; expected_Q = 8'd20;
        checker_scoreboard("Priority_Check");

        $finish;
    end

    initial begin
        $dumpfile("tb_mult_regs.vcd");
        $dumpvars(0, tb_mult_regs);
    end

endmodule

tb_mult_regs.vcd
$date
	Mon Jun 29 16:30:14 2026
$end
$version
	Icarus Verilog
$end
$timescale
	1ps
$end
$scope module tb_mult_regs $end
$var wire 8 ! Q [7:0] $end
$var wire 8 " M [7:0] $end
$var wire 9 # A [8:0] $end
$var reg 8 $ a_in [7:0] $end
$var reg 1 % add_en $end
$var reg 8 & b_in [7:0] $end
$var reg 1 ' clk $end
$var reg 9 ( expected_A [8:0] $end
$var reg 8 ) expected_M [7:0] $end
$var reg 8 * expected_Q [7:0] $end
$var reg 1 + load $end
$var reg 1 , rst $end
$var reg 1 - shift $end
$var reg 9 . sum [8:0] $end
$scope module dut $end
$var wire 8 / a_in [7:0] $end
$var wire 1 % add_en $end
$var wire 8 0 b_in [7:0] $end
$var wire 1 ' clk $end
$var wire 1 + load $end
$var wire 1 , rst $end
$var wire 1 - shift $end
$var wire 9 1 sum [8:0] $end
$var reg 9 2 A [8:0] $end
$var reg 8 3 M [7:0] $end
$var reg 8 4 Q [7:0] $end
$upscope $end
$scope task checker_scoreboard $end
$upscope $end
$upscope $end
$enddefinitions $end
$comment Show the parameter values. $end
$dumpall
$end
#0
$dumpvars
b0 4
b0 3
b0 2
b0 1
b0 0
b0 /
b0 .
0-
1,
0+
b0 *
b0 )
b0 (
0'
b0 &
0%
b0 $
b0 #
b0 "
b0 !
$end
#5000
1'
#10000
0'
#15000
1'
#16000
b1100 &
b1100 0
b101101 $
b101101 /
1+
0,
#20000
0'
#25000
b1100 !
b1100 4
b101101 "
b101101 3
1'
#26000
1%
b10000111 .
b10000111 1
b1100 *
b101101 )
0+
#30000
0'
#35000
b10000111 #
b10000111 2
1'
#36000
b10000110 *
1-
b1000011 (
0%
#40000
0'
#45000
b1000011 #
b1000011 2
b10000110 !
b10000110 4
1'
#46000
b100001 (
b11000011 *
1-
#50000
0'
#55000
b100001 #
b100001 2
b11000011 !
b11000011 4
1'
#56000
b110010 .
b110010 1
b10100 &
b10100 0
b1010 $
b1010 /
1%
1+
1-
#60000
0'
#65000
b10100 !
b10100 4
b1010 "
b1010 3
b0 #
b0 2
1'
#66000
b10100 *
b1010 )
b0 (
0-
0%
0+
